agora/__init__.py
agora/common/__init__.py
agora/common/core.py
agora/common/errors.py
agora/common/executor.py
agora/common/function_schema.py
agora/common/interpreters/restricted.py
agora/common/memory.py
agora/common/storage.py
agora/common/toolformers/__init__.py
agora/common/toolformers/base.py
agora/common/toolformers/camel.py
agora/common/toolformers/langchain.py
agora/receiver/__init__.py
agora/receiver/components/negotiator.py
agora/receiver/components/programmer.py
agora/receiver/components/protocol_checker.py
agora/receiver/components/responder.py
agora/receiver/core.py
agora/receiver/memory.py
agora/receiver/server.py
agora/sender/__init__.py
agora/sender/components/negotiator.py
agora/sender/components/programmer.py
agora/sender/components/protocol_picker.py
agora/sender/components/querier.py
agora/sender/components/transporter.py
agora/sender/core.py
agora/sender/memory.py
agora/sender/schema_generator.py
agora/sender/task_schema.py
agora/utils.py
agora_protocol-0.2.0.dist-info/LICENSE
agora_protocol-0.2.0.dist-info/METADATA
agora_protocol-0.2.0.dist-info/WHEEL
agora_protocol-0.2.0.dist-info/RECORD
