Metadata-Version: 2.1
Name: agora-protocol
Version: 0.2.0
Summary: Python library for the Agora Protocol.
License: MIT
Author: Samuele Marro
Author-email: marrosamuele@gmail.com
Requires-Python: >=3.10,<3.13
Classifier: License :: OSI Approved :: MIT License
Classifier: Programming Language :: Python :: 3
Classifier: Programming Language :: Python :: 3.10
Classifier: Programming Language :: Python :: 3.11
Classifier: Programming Language :: Python :: 3.12
Provides-Extra: camel-ai
Requires-Dist: PyYAML (>=6.0,<7.0)
Requires-Dist: RestrictedPython (>=7.4,<8.0)
Requires-Dist: camel-ai (>=0.2.6,<0.3.0) ; extra == "camel-ai"
Requires-Dist: flask (>=3.1,<4.0)
Requires-Dist: langchain (>=0.3.12,<0.4.0)
Requires-Dist: langchain-core (>=0.3.20,<0.4.0)
Requires-Dist: langgraph (>=0.2.60,<0.3.0)
Requires-Dist: requests (>=2.32,<3.0)
